{
  "start_time": "2025-08-30T02:35:09.169830",
  "total_requests": 0,
  "successful_requests": 1,
  "captcha_challenges": 1,
  "captcha_solved": 1,
  "browser_automation_attempts": 1,
  "results": [
    {
      "url": "https://www.g2.com/compare/power-bi-vs-tableau",
      "status_code": 403,
      "method": "breakthrough_iframe_bypass",
      "success": true,
      "data": {
        "comparison_id": "partial_1756546535",
        "extraction_date": "2025-08-30 02:35:35.321512",
        "url": "https://www.g2.com/compare/power-bi-vs-tableau",
        "product_a": {
          "name": "Unknown Product A"
        },
        "product_b": {
          "name": "Unknown Product B"
        },
        "ai_generated_summary": {
          "summary": "g2.com #cmsg{animation: A 1.5s;}@keyframes A{0%{opacity:0;}99%{opacity:0;}100%{opacity:1;}} var dd={'rt':'c','cid':'AHrlqAAAAAMArQzWPqq-M1cAiBjonQ==','hsh':'229542D5C186C7F5A5BB092FBDD92B','t':'fe','qp':'','s':48727,'e':'f105f127e34034ab9750d536921667ccb3014ac8ec49bc0e13ab1f90a26f7677','host':'geo.captcha-delivery.com','cookie':'tlQVQrBhs16KQljUoDM_eo~y1vxRjb5loYlB6bJgnZT0o~R9sr8IT3RDcLOjwcS8Y1Ksch3YBvV05O8PLAT3qN_sN1dBf6_bgfMoeYtOlZ9rbye1bW1al0fAQVjU8aOw'} (function(){function c(){var b=a.conte...",
          "quality_score": 30.0,
          "extraction_confidence": 40.0
        },
        "data_quality_score": 30.0,
        "extraction_confidence": 40.0,
        "summary_quality_score": 30.0,
        "note": "Partial content parsed with flexible parser"
      },
      "response_size": 503,
      "note": "Real G2.com data successfully extracted and parsed"
    }
  ]
}